README.rst
setup.py
social/__init__.py
social/facebook.py
social.egg-info/PKG-INFO
social.egg-info/SOURCES.txt
social.egg-info/dependency_links.txt
social.egg-info/top_level.txt